azfunc_boot/__init__.py
azfunc_boot/bootstrap/app_factory.py
azfunc_boot/common/disposable.py
azfunc_boot/common/exceptions/not_found_error.py
azfunc_boot/common/exceptions/validation_error.py
azfunc_boot/config/configuration.py
azfunc_boot/di/dependency_injector.py
azfunc_boot/di/scope.py
azfunc_boot/mvc/base_controller.py
azfunc_boot/mvc/controller_discovery.py
azfunc_boot/mvc/scoped_blueprint.py
azfunc_boot/mvc/trigger_decorator.py
azfunc_boot/mvc/trigger_wrapper.py
azfunc_boot/registry/base_service_registry.py
azfunc_boot/registry/discovery.py
azfunc_boot-1.0.0b1.dist-info/METADATA
azfunc_boot-1.0.0b1.dist-info/WHEEL
azfunc_boot-1.0.0b1.dist-info/RECORD
