Metadata-Version: 2.4
Name: azfunc-boot
Version: 1.0.0b1
Summary: A powerful framework for building Azure Functions applications with built-in dependency injection and controller-based architecture
License: MIT
Keywords: azure,functions,dependency-injection,framework,mvc
Author: Santiago Vasquez Gomez
Author-email: santivasquez1@gmail.com
Requires-Python: >=3.11,<4.0
Classifier: Development Status :: 4 - Beta
Classifier: Intended Audience :: Developers
Classifier: License :: OSI Approved :: MIT License
Classifier: Programming Language :: Python :: 3
Classifier: Programming Language :: Python :: 3.11
Classifier: Programming Language :: Python :: 3.12
Classifier: Programming Language :: Python :: 3.13
Classifier: Programming Language :: Python :: 3.14
Classifier: Topic :: Internet :: WWW/HTTP :: HTTP Servers
Classifier: Topic :: Software Development :: Libraries :: Python Modules
Requires-Dist: azure-functions (>=1.21.0,<2.0.0)
Project-URL: Homepage, https://github.com/santiagovasquez1/azfunc-boot
Project-URL: Repository, https://github.com/santiagovasquez1/azfunc-boot
